LICENSE
MANIFEST.in
README.md
package.json
setup.py
dash_echarts_tradenexus/DashECharts.py
dash_echarts_tradenexus/__init__.py
dash_echarts_tradenexus/_imports_.py
dash_echarts_tradenexus/async-null.js
dash_echarts_tradenexus/async-null.js.map
dash_echarts_tradenexus/dash_echarts_tradenexus.min.js
dash_echarts_tradenexus/dash_echarts_tradenexus.min.js.map
dash_echarts_tradenexus/metadata.json
dash_echarts_tradenexus/package-info.json
dash_echarts_tradenexus.egg-info/PKG-INFO
dash_echarts_tradenexus.egg-info/SOURCES.txt
dash_echarts_tradenexus.egg-info/dependency_links.txt
dash_echarts_tradenexus.egg-info/top_level.txt
tests/test_usage.py