Metadata-Version: 2.2
Name: dash_echarts_tradenexus
Version: 0.0.4
Summary: A custom Dash component for Echarts
Author: Waleed Malik <zenalytiks@gmail.com>
License: MIT
Classifier: Framework :: Dash
License-File: LICENSE
Dynamic: author
Dynamic: classifier
Dynamic: description
Dynamic: description-content-type
Dynamic: license
Dynamic: summary
